{"nodes": [{"id": "docs_reviews_m5_r4_m5_summary", "label": "R4 CodeRabbit Review Summary \u2014 M5", "file_type": "document", "source_file": "docs/reviews/m5/R4-M5-summary.md", "source_location": null, "source_url": null, "captured_at": null, "author": null, "contributor": null}, {"id": "docs_reviews_m5_r4_m5_summary_n1_finding", "label": "CoreContentRepository N+1 Note Loading Finding", "file_type": "rationale", "source_file": "docs/reviews/m5/R4-M5-summary.md", "source_location": null, "source_url": null, "captured_at": null, "author": null, "contributor": null}, {"id": "docs_reviews_m5_r4_m5_summary_payload_bounds_finding", "label": "Unbounded Note/Checklist Payload Limits Finding", "file_type": "rationale", "source_file": "docs/reviews/m5/R4-M5-summary.md", "source_location": null, "source_url": null, "captured_at": null, "author": null, "contributor": null}], "edges": [{"source": "docs_reviews_m5_r4_m5_summary_n1_finding", "target": "docs_reviews_m5_r4_m5_summary", "relation": "rationale_for", "confidence": "EXTRACTED", "confidence_score": 1.0, "source_file": "docs/reviews/m5/R4-M5-summary.md", "source_location": null, "weight": 1.0}, {"source": "docs_reviews_m5_r4_m5_summary_payload_bounds_finding", "target": "docs_reviews_m5_r4_m5_summary", "relation": "rationale_for", "confidence": "EXTRACTED", "confidence_score": 1.0, "source_file": "docs/reviews/m5/R4-M5-summary.md", "source_location": null, "weight": 1.0}, {"source": "docs_reviews_m5_r4_m5_summary", "target": "docs_reviews_m4_r3_m4_summary", "relation": "references", "confidence": "EXTRACTED", "confidence_score": 1.0, "source_file": "docs/reviews/m5/R4-M5-summary.md", "source_location": null, "weight": 1.0}, {"source": "docs_reviews_m5_r4_m5_summary", "target": "docs_reviews_m3_r2_m3_summary", "relation": "references", "confidence": "EXTRACTED", "confidence_score": 1.0, "source_file": "docs/reviews/m5/R4-M5-summary.md", "source_location": null, "weight": 1.0}, {"source": "docs_reviews_m5_r4_m5_summary", "target": "docs_reviews_m2_r1_m2_summary", "relation": "references", "confidence": "EXTRACTED", "confidence_score": 1.0, "source_file": "docs/reviews/m5/R4-M5-summary.md", "source_location": null, "weight": 1.0}, {"source": "docs_reviews_m5_r4_m5_summary", "target": "docs_reviews_m1_r0_m1_summary", "relation": "references", "confidence": "EXTRACTED", "confidence_score": 1.0, "source_file": "docs/reviews/m5/R4-M5-summary.md", "source_location": null, "weight": 1.0}, {"source": "docs_reviews_m5_r4_m5_summary", "target": "docs_reviews_remediation_batch_4_b4_persistence_contracts_summary", "relation": "references", "confidence": "EXTRACTED", "confidence_score": 1.0, "source_file": "docs/reviews/m5/R4-M5-summary.md", "source_location": null, "weight": 1.0}], "hyperedges": []}